pyjd/__init__.py
pyjd/accounts.py
pyjd/captcha.py
pyjd/config.py
pyjd/content.py
pyjd/device.py
pyjd/dialogs.py
pyjd/direct_connection_helper.py
pyjd/direct_connector.py
pyjd/downloads.py
pyjd/events.py
pyjd/extensions.py
pyjd/jd_device.py
pyjd/jd_types.py
pyjd/linkgrabber.py
pyjd/log.py
pyjd/myjd_connection_helper.py
pyjd/myjd_connector.py
pyjd/plugins.py
pyjd/polling.py
pyjd/system.py
pyjd/toolbar.py
pyjd/ui.py
pyjd/update.py
pyjd-1.0.13.dist-info/LICENSE
pyjd-1.0.13.dist-info/METADATA
pyjd-1.0.13.dist-info/WHEEL
pyjd-1.0.13.dist-info/top_level.txt
pyjd-1.0.13.dist-info/RECORD
