Metadata-Version: 2.1
Name: pyjd
Version: 1.0.13
Summary: A wrapper for the JDownloader API
Home-page: https://git.sr.ht/~pglaum/pyjd-api
Author: Philipp Glaum
Author-email: p@pglaum.de
License: GPLv3
Keywords: api jdownloader
Classifier: Programming Language :: Python :: 3
Classifier: Operating System :: OS Independent
Classifier: License :: OSI Approved :: GNU General Public License v3 (GPLv3)
License-File: LICENSE
Requires-Dist: requests
Requires-Dist: pydantic==1.10.19
Requires-Dist: pycryptodome
